voluptuous_openapi/__init__.py
voluptuous_openapi-0.3.0.dist-info/licenses/LICENSE
voluptuous_openapi-0.3.0.dist-info/METADATA
voluptuous_openapi-0.3.0.dist-info/WHEEL
voluptuous_openapi-0.3.0.dist-info/top_level.txt
voluptuous_openapi-0.3.0.dist-info/RECORD
