Metadata-Version: 2.4
Name: voluptuous-openapi
Version: 0.3.0
Summary: Convert voluptuous schemas to OpenAPI Schema object
Author-email: Denis Shulyaka <Shulyaka@gmail.com>
License-Expression: Apache-2.0
Project-URL: Source code, https://github.com/home-assistant-libs/voluptuous-openapi
Requires-Python: >=3.9
License-File: LICENSE
Requires-Dist: voluptuous
Dynamic: license-file
